[{"confidence": "0.8150", "file_id": "73", "bbox": "322 206 688 474"}, {"confidence": "0.7334", "file_id": "94", "bbox": "193 176 848 440"}, {"confidence": "0.7318", "file_id": "43", "bbox": "0 19 1023 532"}, {"confidence": "0.7239", "file_id": "43", "bbox": "21 27 356 229"}, {"confidence": "0.7135", "file_id": "137", "bbox": "115 91 908 576"}, {"confidence": "0.7046", "file_id": "37", "bbox": "62 391 954 759"}, {"confidence": "0.7027", "file_id": "62", "bbox": "937 449 1014 530"}, {"confidence": "0.6808", "file_id": "137", "bbox": "26 131 370 288"}, {"confidence": "0.6781", "file_id": "82", "bbox": "0 128 1021 535"}, {"confidence": "0.6717", "file_id": "87", "bbox": "4 262 132 354"}, {"confidence": "0.6519", "file_id": "87", "bbox": "89 160 931 483"}, {"confidence": "0.6462", "file_id": "125", "bbox": "70 135 942 545"}, {"confidence": "0.6382", "file_id": "119", "bbox": "54 214 963 601"}, {"confidence": "0.6208", "file_id": "76", "bbox": "153 144 859 617"}, {"confidence": "0.6011", "file_id": "79", "bbox": "0 32 148 193"}, {"confidence": "0.5945", "file_id": "11", "bbox": "227 290 497 411"}, {"confidence": "0.5874", "file_id": "105", "bbox": "162 93 989 631"}, {"confidence": "0.5801", "file_id": "7", "bbox": "0 220 882 583"}, {"confidence": "0.5737", "file_id": "137", "bbox": "57 105 484 362"}, {"confidence": "0.5708", "file_id": "11", "bbox": "699 311 829 384"}, {"confidence": "0.5629", "file_id": "16", "bbox": "29 88 996 675"}, {"confidence": "0.5629", "file_id": "107", "bbox": "29 88 996 675"}, {"confidence": "0.5594", "file_id": "37", "bbox": "1 411 113 492"}, {"confidence": "0.5577", "file_id": "82", "bbox": "0 147 104 251"}, {"confidence": "0.5556", "file_id": "38", "bbox": "33 98 381 363"}, {"confidence": "0.5527", "file_id": "67", "bbox": "85 192 925 658"}, {"confidence": "0.5391", "file_id": "39", "bbox": "0 109 1023 767"}, {"confidence": "0.5263", "file_id": "79", "bbox": "126 16 305 185"}, {"confidence": "0.5216", "file_id": "57", "bbox": "63 221 952 650"}, {"confidence": "0.5173", "file_id": "137", "bbox": "609 116 668 144"}, {"confidence": "0.5160", "file_id": "94", "bbox": "860 122 1010 254"}, {"confidence": "0.5152", "file_id": "26", "bbox": "0 18 1023 590"}, {"confidence": "0.4854", "file_id": "57", "bbox": "971 198 1016 226"}, {"confidence": "0.4810", "file_id": "137", "bbox": "42 132 130 182"}, {"confidence": "0.4693", "file_id": "137", "bbox": "645 115 709 152"}, {"confidence": "0.4311", "file_id": "49", "bbox": "151 127 1007 682"}, {"confidence": "0.4055", "file_id": "137", "bbox": "19 135 165 198"}, {"confidence": "0.4020", "file_id": "137", "bbox": "956 122 1023 177"}, {"confidence": "0.3931", "file_id": "84", "bbox": "99 35 919 344"}, {"confidence": "0.3917", "file_id": "108", "bbox": "0 152 1004 763"}, {"confidence": "0.3689", "file_id": "62", "bbox": "818 389 892 434"}, {"confidence": "0.3580", "file_id": "137", "bbox": "497 101 586 131"}, {"confidence": "0.3528", "file_id": "2", "bbox": "125 48 911 430"}, {"confidence": "0.3481", "file_id": "79", "bbox": "66 65 953 590"}, {"confidence": "0.3431", "file_id": "137", "bbox": "4 156 96 219"}, {"confidence": "0.3420", "file_id": "137", "bbox": "578 102 619 128"}, {"confidence": "0.3323", "file_id": "79", "bbox": "60 38 196 85"}, {"confidence": "0.3189", "file_id": "24", "bbox": "181 437 312 498"}, {"confidence": "0.3189", "file_id": "97", "bbox": "181 437 312 498"}, {"confidence": "0.3189", "file_id": "116", "bbox": "181 437 312 498"}, {"confidence": "0.3165", "file_id": "67", "bbox": "58 184 349 390"}, {"confidence": "0.3147", "file_id": "43", "bbox": "17 26 172 107"}, {"confidence": "0.3116", "file_id": "62", "bbox": "944 472 1004 511"}, {"confidence": "0.3064", "file_id": "11", "bbox": "957 238 1023 308"}, {"confidence": "0.3009", "file_id": "57", "bbox": "971 186 1016 215"}]